listslinked/__init__.py
listslinked/circular_doubly_linked_list.py
listslinked/circular_singly_linked_list.py
listslinked/doubly_linked_list.py
listslinked/singly_linked_list.py
listslinked-0.0.2.dist-info/LICENSE
listslinked-0.0.2.dist-info/METADATA
listslinked-0.0.2.dist-info/WHEEL
listslinked-0.0.2.dist-info/top_level.txt
listslinked-0.0.2.dist-info/RECORD
