Metadata-Version: 2.1
Name: listslinked
Version: 0.0.2
Summary: A simple package for linked lists
Author-email: Spyder Rex <billyjohnsonauthor@gmail.com>
Project-URL: Homepage, https://github.com/SpyderRex/listslinked
Project-URL: Issues, https://github.com/Spyder/listslinked/issues
Classifier: Programming Language :: Python :: 3
Classifier: License :: OSI Approved :: MIT License
Classifier: Operating System :: OS Independent
Requires-Python: >=3.8
License-File: LICENSE
